{"peliculas":[{"title":"El señor de los anillos","releaseYear":2005,"nacionality":"estadounidense","genre":"fantasía","actors":[{"name":"Michelle Pfeiffer","age":64,"weight":55,"height":1.68,"isRetired":true,"nationality":"claiforniana","oscarsNumber":2,"profession":"actriz"},{"name":"Mario Casas","age":36,"weight":75,"height":1.82,"isRetired":false,"nationality":"española","oscarsNumber":0,"profession":"actor"},{"name":"Scarlett Johansson","age":38,"weight":57,"height":1.65,"isRetired":false,"nationality":"estadounidense","oscarsNumber":1,"profession":"empresaria"},{"name":"Scarlett Johansson","age":38,"weight":57,"height":1.65,"isRetired":false,"nationality":"estadounidense","oscarsNumber":1,"profession":"empresaria"}],"director":{"name":"Pedro Almodovar","age":64,"weight":82,"height":1.78,"isRetired":false,"nationality":"español","oscarsNumber":2,"profession":"director"},"writer":{"name":"Scarlett Johansson","age":38,"weight":57,"height":1.65,"isRetired":false,"nationality":"estadounidense","oscarsNumber":1,"profession":"empresaria"},"language":"español","plataforma":"Amazon Prime","isMCU":true,"mainCharacterName":"Frodo Bolson","producer":"Nombre productor","distributor":"Nombre distribuidor"},{"title":"Piratas del Caribe","releaseYear":2005,"nacionality":"estadounidense","genre":"fantasía","actors":[{"name":"Michelle Pfeiffer","age":64,"weight":55,"height":1.68,"isRetired":true,"nationality":"claiforniana","oscarsNumber":2,"profession":"actriz"},{"name":"Mario Casas","age":36,"weight":75,"height":1.82,"isRetired":false,"nationality":"española","oscarsNumber":0,"profession":"actor"},{"name":"Scarlett Johansson","age":38,"weight":57,"height":1.65,"isRetired":false,"nationality":"estadounidense","oscarsNumber":1,"profession":"empresaria"},{"name":"Scarlett Johansson","age":38,"weight":57,"height":1.65,"isRetired":false,"nationality":"estadounidense","oscarsNumber":1,"profession":"empresaria"},{"name":"ugutugjhf*******","age":34,"weight":47,"height":1.56,"isRetired":false,"nationality":"lkhga","oscarsNumber":9,"profession":"actriz"}],"director":{"name":"Pedro Almodovar","age":64,"weight":82,"height":1.78,"isRetired":false,"nationality":"español","oscarsNumber":2,"profession":"director"},"writer":{"name":"Scarlett Johansson","age":38,"weight":57,"height":1.65,"isRetired":false,"nationality":"estadounidense","oscarsNumber":1,"profession":"empresaria"},"language":"español","plataforma":"Amazon Prime","isMCU":true,"mainCharacterName":"Frodo Bolson","producer":"Nombre productor","distributor":"Nombre distribuidor"},{"title":"El señor de los anillos","releaseYear":2005,"nacionality":"estadounidense","genre":"fantasía","actors":[{"name":"Michelle Pfeiffer","age":64,"weight":55,"height":1.68,"isRetired":true,"nationality":"claiforniana","oscarsNumber":2,"profession":"actriz"},{"name":"Mario Casas","age":36,"weight":75,"height":1.82,"isRetired":false,"nationality":"española","oscarsNumber":0,"profession":"actor"},{"name":"Scarlett Johansson","age":38,"weight":57,"height":1.65,"isRetired":false,"nationality":"estadounidense","oscarsNumber":1,"profession":"empresaria"},{"name":"Scarlett Johansson","age":38,"weight":57,"height":1.65,"isRetired":false,"nationality":"estadounidense","oscarsNumber":1,"profession":"empresaria"}],"director":{"name":"Pedro Almodovar","age":64,"weight":82,"height":1.78,"isRetired":false,"nationality":"español","oscarsNumber":2,"profession":"director"},"writer":{"name":"Scarlett Johansson","age":38,"weight":57,"height":1.65,"isRetired":false,"nationality":"estadounidense","oscarsNumber":1,"profession":"empresaria"},"language":"español","plataforma":"Amazon Prime","isMCU":true,"mainCharacterName":"Frodo Bolson","producer":"Nombre productor","distributor":"Nombre distribuidor"}]}